osc_physrisk_financial-0.1.1.dist-info/METADATA
osc_physrisk_financial-0.1.1.dist-info/WHEEL
osc_physrisk_financial-0.1.1.dist-info/entry_points.txt
osc_physrisk_financial-0.1.1.dist-info/licenses/LICENSE.txt
osc_physrisk_financial/__init__.py
osc_physrisk_financial/_version.py
osc_physrisk_financial/assets.py
osc_physrisk_financial/dynamics.py
osc_physrisk_financial/functions.py
osc_physrisk_financial/random_variables.py
osc_physrisk_financial-0.1.1.dist-info/RECORD
