Metadata-Version: 2.1
Name: osc-physrisk-financial
Version: 0.1.1
Summary: Physical climate risk financial valuation
Keywords: Financial risk,climate,Physical risk
Author-Email: Arfima Dev <dev@arfima.com>
License: Apache-2.0
Classifier: Development Status :: 4 - Beta
Classifier: Programming Language :: Python
Project-URL: Homepage, https://github.com/os-climate/osc-physrisk-financial
Project-URL: Documentation, https://github.com/os-climate/osc-physrisk-financial
Project-URL: Bug tracker, https://github.com/os-climate/osc-physrisk-financial/issues
Requires-Python: >=3.10
Requires-Dist: scipy>=1.10.1
Requires-Dist: pandas>=2.0.3
Requires-Dist: plotly>=5.15
Requires-Dist: numpy>=1.24
Provides-Extra: docs
Requires-Dist: myst_parser>=3.0.1; extra == "docs"
Requires-Dist: pydata_sphinx_theme>=0.15.4; extra == "docs"
Requires-Dist: sphinx>=7.3.7; extra == "docs"
Requires-Dist: sphinx_design>=0.6.0; extra == "docs"
Provides-Extra: lint
Requires-Dist: pre-commit; extra == "lint"
Provides-Extra: test
Requires-Dist: pdm[pytest]; extra == "test"
Requires-Dist: pytest; extra == "test"
Requires-Dist: pytest-cov; extra == "test"
Provides-Extra: tox
Requires-Dist: tox; extra == "tox"
Requires-Dist: tox-pdm; extra == "tox"
